pydra/__init__.py
pydra/_version.py
pydra/conftest.py
pydra/engine/__init__.py
pydra/engine/audit.py
pydra/engine/boutiques.py
pydra/engine/core.py
pydra/engine/environments.py
pydra/engine/graph.py
pydra/engine/helpers.py
pydra/engine/helpers_file.py
pydra/engine/helpers_state.py
pydra/engine/run_pickled.py
pydra/engine/specs.py
pydra/engine/state.py
pydra/engine/submitter.py
pydra/engine/task.py
pydra/engine/workers.py
pydra/engine/tests/__init__.py
pydra/engine/tests/conftest.py
pydra/engine/tests/test_boutiques.py
pydra/engine/tests/test_dockertask.py
pydra/engine/tests/test_environments.py
pydra/engine/tests/test_graph.py
pydra/engine/tests/test_helpers.py
pydra/engine/tests/test_helpers_file.py
pydra/engine/tests/test_helpers_state.py
pydra/engine/tests/test_nipype1_convert.py
pydra/engine/tests/test_node_task.py
pydra/engine/tests/test_numpy_examples.py
pydra/engine/tests/test_profiles.py
pydra/engine/tests/test_shelltask.py
pydra/engine/tests/test_shelltask_inputspec.py
pydra/engine/tests/test_singularity.py
pydra/engine/tests/test_specs.py
pydra/engine/tests/test_state.py
pydra/engine/tests/test_submitter.py
pydra/engine/tests/test_task.py
pydra/engine/tests/test_tasks_files.py
pydra/engine/tests/test_workflow.py
pydra/engine/tests/utils.py
pydra/engine/tests/data_tests/loading.py
pydra/engine/tests/data_tests/saving.py
pydra/engine/tests/data_tests/test.nii.gz
pydra/mark/__init__.py
pydra/mark/functions.py
pydra/mark/tests/__init__.py
pydra/mark/tests/test_functions.py
pydra/schema/context.jsonld
pydra/tasks/__init__.py
pydra/utils/__init__.py
pydra/utils/hash.py
pydra/utils/messenger.py
pydra/utils/misc.py
pydra/utils/profiler.py
pydra/utils/typing.py
pydra/utils/tests/__init__.py
pydra/utils/tests/test_hash.py
pydra/utils/tests/test_messenger.py
pydra/utils/tests/test_profiler.py
pydra/utils/tests/test_typing.py
pydra/utils/tests/utils.py
pydra-0.25.dist-info/LICENSE
pydra-0.25.dist-info/WHEEL
pydra-0.25.dist-info/METADATA
pydra-0.25.dist-info/RECORD
