Metadata-Version: 2.3
Name: pydra
Version: 0.25
Summary: Pydra dataflow engine
Keywords: brainweb,dataflow,neuroimaging,pydra
Author-email: Nipype developers <neuroimaging@python.org>
Maintainer-email: Nipype developers <neuroimaging@python.org>
Requires-Python: >=3.8
Classifier: Development Status :: 3 - Alpha
Classifier: Environment :: Console
Classifier: Intended Audience :: Science/Research
Classifier: License :: OSI Approved :: Apache Software License
Classifier: Operating System :: MacOS :: MacOS X
Classifier: Operating System :: Microsoft :: Windows
Classifier: Operating System :: POSIX :: Linux
Classifier: Programming Language :: Python :: 3.7
Classifier: Programming Language :: Python :: 3.8
Classifier: Programming Language :: Python :: 3.9
Classifier: Programming Language :: Python :: 3.10
Classifier: Programming Language :: Python :: 3.11
Classifier: Topic :: Scientific/Engineering
Requires-Dist: attrs >=19.1.0
Requires-Dist: cloudpickle >=2.0.0
Requires-Dist: etelemetry >=0.2.2
Requires-Dist: filelock >=3.0.0
Requires-Dist: fileformats >=0.8
Requires-Dist: importlib_resources >=5.7; python_version < '3.11'
Requires-Dist: platformdirs >=2
Requires-Dist: typing_extensions >=4.6.3; python_version < '3.10'
Requires-Dist: typing_utils >=0.1.0; python_version < '3.10'
Requires-Dist: pydra[doc, dev] ; extra == "all"
Requires-Dist: dask ; extra == "dask"
Requires-Dist: distributed ; extra == "dask"
Requires-Dist: black ; extra == "dev"
Requires-Dist: pre-commit ; extra == "dev"
Requires-Dist: pydra[test] ; extra == "dev"
Requires-Dist: packaging ; extra == "doc"
Requires-Dist: sphinx ==6.2.1 ; extra == "doc"
Requires-Dist: sphinx_rtd_theme ; extra == "doc"
Requires-Dist: sphinxcontrib-apidoc ~=0.3.0 ; extra == "doc"
Requires-Dist: sphinxcontrib-versioning ; extra == "doc"
Requires-Dist: pydra[doc] ; extra == "docs"
Requires-Dist: nest_asyncio ; extra == "jupyter"
Requires-Dist: psij-python ; extra == "psij"
Requires-Dist: pytest >=6.2.5 ; extra == "test"
Requires-Dist: pytest-cov ; extra == "test"
Requires-Dist: pytest-env ; extra == "test"
Requires-Dist: pytest-xdist <2.0 ; extra == "test"
Requires-Dist: pytest-rerunfailures ; extra == "test"
Requires-Dist: pytest-timeout ; extra == "test"
Requires-Dist: codecov ; extra == "test"
Requires-Dist: numpy ; extra == "test"
Requires-Dist: pyld ; extra == "test"
Requires-Dist: psutil ; extra == "test"
Requires-Dist: python-dateutil ; extra == "test"
Requires-Dist: tornado ; extra == "test"
Requires-Dist: boutiques ; extra == "test"
Requires-Dist: pympler ; extra == "test"
Requires-Dist: pydra[test] ; extra == "tests"
Project-URL: documentation, https://nipype.github.io/pydra/
Project-URL: homepage, https://nipype.github.io/pydra/
Project-URL: repository, https://github.com/nipype/pydra.git
Provides-Extra: all
Provides-Extra: dask
Provides-Extra: dev
Provides-Extra: doc
Provides-Extra: docs
Provides-Extra: jupyter
Provides-Extra: psij
Provides-Extra: test
Provides-Extra: tests
